cymbal/__init__.py
cymbal/clangext.py
cymbal-1.0.0.dist-info/DESCRIPTION.rst
cymbal-1.0.0.dist-info/METADATA
cymbal-1.0.0.dist-info/RECORD
cymbal-1.0.0.dist-info/WHEEL
cymbal-1.0.0.dist-info/metadata.json
cymbal-1.0.0.dist-info/top_level.txt
tests/__init__.py
tests/test_clang_extensions.py
